[
  1,
  [
    "14952920c",
    "e0pTt+r3VMBYQYFLPTg6Rz"
  ],
  [
    "_textureSetter"
  ],
  [
    "cc.SpriteFrame"
  ],
  0,
  [
    [
      [
        {
          "name": "g50_com_pl_03",
          "rect": [
            1514,
            3,
            458,
            103
          ],
          "offset": [
            0,
            0
          ],
          "originalSize": [
            458,
            103
          ],
          "capInsets": [
            80,
            0,
            80,
            0
          ]
        }
      ],
      [
        0
      ],
      0,
      [
        0
      ],
      [
        0
      ],
      [
        0
      ]
    ],
    [
      [
        {
          "name": "g50_com_pl_01",
          "rect": [
            0,
            0,
            669,
            407
          ],
          "offset": [
            0,
            0
          ],
          "originalSize": [
            669,
            407
          ],
          "capInsets": [
            60,
            60,
            60,
            60
          ]
        }
      ],
      [
        0
      ],
      0,
      [
        0
      ],
      [
        0
      ],
      [
        1
      ]
    ],
    [
      [
        {
          "name": "g50_com_btn_01",
          "rect": [
            208,
            1741,
            234,
            68
          ],
          "offset": [
            0,
            0
          ],
          "originalSize": [
            234,
            68
          ],
          "rotated": 1,
          "capInsets": [
            55,
            0,
            55,
            0
          ]
        }
      ],
      [
        0
      ],
      0,
      [
        0
      ],
      [
        0
      ],
      [
        0
      ]
    ]
  ]
]